dxf/__init__.py
dxf/__main__.py
dxf/exceptions.py
dxf/main.py
dxf/py.typed
python_dxf-12.1.0.dist-info/LICENCE
python_dxf-12.1.0.dist-info/METADATA
python_dxf-12.1.0.dist-info/WHEEL
python_dxf-12.1.0.dist-info/entry_points.txt
python_dxf-12.1.0.dist-info/top_level.txt
python_dxf-12.1.0.dist-info/RECORD
