Metadata-Version: 2.1
Name: python-dxf
Version: 12.1.0
Summary: Package for accessing a Docker v2 registry
Home-page: https://github.com/davedoesdev/dxf
Author: David Halls
Author-email: dave@davedoesdev.com
License: MIT
Keywords: docker registry
Requires-Python: >=3.8
License-File: LICENCE
Requires-Dist: www-authenticate >=0.9.2
Requires-Dist: requests >=2.18.4
Requires-Dist: tqdm >=4.19.4
